SAAVpedia/ClassSAAVpedia.py
SAAVpedia/__init__.py
SAAVpedia/db/ClassLocalDB.bak.py
SAAVpedia/db/ClassLocalDB.py
SAAVpedia/db/ClassOnlineDB-2.py
SAAVpedia/db/ClassOnlineDB.py
SAAVpedia/db/ClassSAAVpediaInputParser.py
SAAVpedia/db/ClassSQLite3.py
SAAVpedia/db/__init__.py
SAAVpedia/db/assign.py
SAAVpedia/dta/ClassDTASelectFilter.py
SAAVpedia/dta/__init__.py
SAAVpedia-0.7.2.dist-info/DESCRIPTION.rst
SAAVpedia-0.7.2.dist-info/METADATA
SAAVpedia-0.7.2.dist-info/RECORD
SAAVpedia-0.7.2.dist-info/WHEEL
SAAVpedia-0.7.2.dist-info/metadata.json
SAAVpedia-0.7.2.dist-info/top_level.txt
demo/__init__.py
demo/SAAVpedia/__init__.py
demo/SAAVpedia/scripts/SAAVidentifier-Online.py
demo/SAAVpedia/scripts/SAAVidentifier.py
demo/SAAVpedia/scripts/SAAVinterpreter-Online.py
demo/SAAVpedia/scripts/SAAVinterpreter.py
demo/SAAVpedia/scripts/SAAVretriever-Online.py
demo/SAAVpedia/scripts/SAAVretriever.py
demo/SAAVpedia/scripts/SNVretriever-Online.py
demo/SAAVpedia/scripts/SNVretriever.py
demo/SAAVpedia/scripts/__init__.py
