Metadata-Version: 2.0
Name: SAAVpedia
Version: 0.7.2
Summary: SAAVpedia python library
Home-page: https://github.com/SAAVpedia/python
Author: Young-Mook Kang
Author-email: ymkang@thylove.org
License: APACHE 2.0
Platform: UNKNOWN
Requires-Dist: datetime
Requires-Dist: nose
Requires-Dist: requests
